{"models":[{"id":2133157,"name":"10/28/2011","type":"Ride","display_type":"Sortie à vélo","activity_type_display_name":"Sortie à vélo","private":false,"bike_id":16587,"athlete_gear_id":null,"start_date":"ven. 28/10/2011","start_date_local_raw":1319809823,"start_time":"2011-10-28T17:50:23+0000","start_day":"Fri","distance":"10,0","distance_raw":10036.7,"long_unit":"kilomètres","short_unit":"km","moving_time":"51:54","moving_time_raw":3114,"elapsed_time":"57:09","elapsed_time_raw":3429,"trainer":false,"static_map":true,"show_elevation":true,"has_latlng":true,"commute":false,"elevation_gain":"320","elevation_unit":"m","elevation_gain_raw":319.889,"description":"","activity_url":"https://www.strava.com/activities/2133157","activity_url_for_twitter":"https://www.strava.com/activities/2133157?utm_content=57341\u0026utm_medium=referral\u0026utm_source=twitter","twitter_msg":"a parcouru 10,0 kilomètre sur Sortie à vélo.","is_new":false,"is_changing_type":false,"suffer_score":null,"calories":null,"feed_data":{"entries":[]},"workout_type":null,"flagged":false,"hide_power":false,"hide_heartrate":false,"segment_leaderboard_opt_out":false},{"id":2080207,"name":"10/23/2011","type":"Ride","display_type":"Sortie à vélo","activity_type_display_name":"Sortie à vélo","private":false,"bike_id":16587,"athlete_gear_id":null,"start_date":"dim. 23/10/2011","start_date_local_raw":1319385474,"start_time":"2011-10-23T19:57:54+0000","start_day":"Sun","distance":"6,5","distance_raw":6535.62,"long_unit":"kilomètres","short_unit":"km","moving_time":"48:57","moving_time_raw":2937,"elapsed_time":"52:42","elapsed_time_raw":3162,"trainer":false,"static_map":true,"show_elevation":true,"has_latlng":true,"commute":false,"elevation_gain":"329","elevation_unit":"m","elevation_gain_raw":328.577,"description":"","activity_url":"https://www.strava.com/activities/2080207","activity_url_for_twitter":"https://www.strava.com/activities/2080207?utm_content=57341\u0026utm_medium=referral\u0026utm_source=twitter","twitter_msg":"a parcouru 6,5 kilomètre sur Sortie à vélo.","is_new":false,"is_changing_type":false,"suffer_score":null,"calories":null,"feed_data":{"entries":[]},"workout_type":null,"flagged":false,"hide_power":false,"hide_heartrate":false,"segment_leaderboard_opt_out":false},{"id":2063352,"name":"10/22/2011","type":"Run","display_type":"Course","activity_type_display_name":"Course à pied","private":false,"bike_id":null,"athlete_gear_id":null,"start_date":"sam. 22/10/2011","start_date_local_raw":1319290860,"start_time":"2011-10-22T17:41:00+0000","start_day":"Sat","distance":"5,4","distance_raw":5431.17,"long_unit":"kilomètres","short_unit":"km","moving_time":"37:34","moving_time_raw":2254,"elapsed_time":"38:24","elapsed_time_raw":2304,"trainer":false,"static_map":true,"show_elevation":true,"has_latlng":true,"commute":null,"elevation_gain":"84","elevation_unit":"m","elevation_gain_raw":84.0523,"description":"","activity_url":"https://www.strava.com/activities/2063352","activity_url_for_twitter":"https://www.strava.com/activities/2063352?utm_content=57341\u0026utm_medium=referral\u0026utm_source=twitter","twitter_msg":"a parcouru 5,4 kilomètre sur Course à pied.","is_new":false,"is_changing_type":false,"suffer_score":null,"calories":1365.9240474720004,"feed_data":{"entries":[]},"workout_type":null,"flagged":false,"hide_power":false,"hide_heartrate":false,"segment_leaderboard_opt_out":false},{"id":1820134,"name":"10/01/2011","type":"Run","display_type":"Course","activity_type_display_name":"Course à pied","private":false,"bike_id":null,"athlete_gear_id":null,"start_date":"sam. 1/10/2011","start_date_local_raw":1317480783,"start_time":"2011-10-01T18:53:03+0000","start_day":"Sat","distance":"5,1","distance_raw":5122.75,"long_unit":"kilomètres","short_unit":"km","moving_time":"32:33","moving_time_raw":1953,"elapsed_time":"32:33","elapsed_time_raw":1953,"trainer":false,"static_map":true,"show_elevation":true,"has_latlng":true,"commute":null,"elevation_gain":"118","elevation_unit":"m","elevation_gain_raw":117.867,"description":"with poussette!","activity_url":"https://www.strava.com/activities/1820134","activity_url_for_twitter":"https://www.strava.com/activities/1820134?utm_content=57341\u0026utm_medium=referral\u0026utm_source=twitter","twitter_msg":"a parcouru 5,1 kilomètre sur Course à pied.","is_new":false,"is_changing_type":false,"suffer_score":null,"calories":1210.05075384,"feed_data":{"entries":[]},"workout_type":null,"flagged":false,"hide_power":false,"hide_heartrate":false,"segment_leaderboard_opt_out":false},{"id":1750749,"name":"09/25/2011","type":"Run","display_type":"Course","activity_type_display_name":"Course à pied","private":false,"bike_id":null,"athlete_gear_id":null,"start_date":"dim. 25/9/2011","start_date_local_raw":1316959572,"start_time":"2011-09-25T18:06:12+0000","start_day":"Sun","distance":"4,2","distance_raw":4234.85,"long_unit":"kilomètres","short_unit":"km","moving_time":"35:34","moving_time_raw":2134,"elapsed_time":"40:03","elapsed_time_raw":2403,"trainer":false,"static_map":true,"show_elevation":true,"has_latlng":true,"commute":null,"elevation_gain":"215","elevation_unit":"m","elevation_gain_raw":214.727,"description":"","activity_url":"https://www.strava.com/activities/1750749","activity_url_for_twitter":"https://www.strava.com/activities/1750749?utm_content=57341\u0026utm_medium=referral\u0026utm_source=twitter","twitter_msg":"a parcouru 4,2 kilomètre sur Course à pied.","is_new":false,"is_changing_type":false,"suffer_score":null,"calories":1141.9543594079998,"feed_data":{"entries":[]},"workout_type":null,"flagged":false,"hide_power":false,"hide_heartrate":false,"segment_leaderboard_opt_out":false},{"id":1686847,"name":"09/19/2011","type":"Run","display_type":"Course","activity_type_display_name":"Course à pied","private":false,"bike_id":null,"athlete_gear_id":null,"start_date":"lun. 19/9/2011","start_date_local_raw":1316466247,"start_time":"2011-09-20T01:04:07+0000","start_day":"Mon","distance":"3,7","distance_raw":3798.44,"long_unit":"kilomètres","short_unit":"km","moving_time":"23:21","moving_time_raw":1401,"elapsed_time":"23:21","elapsed_time_raw":1401,"trainer":false,"static_map":true,"show_elevation":true,"has_latlng":true,"commute":null,"elevation_gain":"53","elevation_unit":"m","elevation_gain_raw":52.9851,"description":"","activity_url":"https://www.strava.com/activities/1686847","activity_url_for_twitter":"https://www.strava.com/activities/1686847?utm_content=57341\u0026utm_medium=referral\u0026utm_source=twitter","twitter_msg":"a parcouru 3,7 kilomètre sur Course à pied.","is_new":false,"is_changing_type":false,"suffer_score":null,"calories":913.8037190399999,"feed_data":{"entries":[]},"workout_type":null,"flagged":false,"hide_power":false,"hide_heartrate":false,"segment_leaderboard_opt_out":false},{"id":1511220,"name":"09/05/2011","type":"Run","display_type":"Course","activity_type_display_name":"Course à pied","private":false,"bike_id":null,"athlete_gear_id":null,"start_date":"lun. 5/9/2011","start_date_local_raw":1315234858,"start_time":"2011-09-05T19:00:58+0000","start_day":"Mon","distance":"4,3","distance_raw":4351.88,"long_unit":"kilomètres","short_unit":"km","moving_time":"31:50","moving_time_raw":1910,"elapsed_time":"36:30","elapsed_time_raw":2190,"trainer":false,"static_map":true,"show_elevation":true,"has_latlng":true,"commute":null,"elevation_gain":"206","elevation_unit":"m","elevation_gain_raw":205.97,"description":"","activity_url":"https://www.strava.com/activities/1511220","activity_url_for_twitter":"https://www.strava.com/activities/1511220?utm_content=57341\u0026utm_medium=referral\u0026utm_source=twitter","twitter_msg":"a parcouru 4,3 kilomètre sur Course à pied.","is_new":false,"is_changing_type":false,"suffer_score":null,"calories":1239.4560150720001,"feed_data":{"entries":[]},"workout_type":null,"flagged":false,"hide_power":false,"hide_heartrate":false,"segment_leaderboard_opt_out":false},{"id":1499335,"name":"09/04/2011","type":"Run","display_type":"Course","activity_type_display_name":"Course à pied","private":false,"bike_id":null,"athlete_gear_id":null,"start_date":"dim. 4/9/2011","start_date_local_raw":1315151460,"start_time":"2011-09-04T19:51:00+0000","start_day":"Sun","distance":"5,5","distance_raw":5556.76,"long_unit":"kilomètres","short_unit":"km","moving_time":"38:40","moving_time_raw":2320,"elapsed_time":"42:01","elapsed_time_raw":2521,"trainer":false,"static_map":true,"show_elevation":true,"has_latlng":true,"commute":null,"elevation_gain":"219","elevation_unit":"m","elevation_gain_raw":219.493,"description":"","activity_url":"https://www.strava.com/activities/1499335","activity_url_for_twitter":"https://www.strava.com/activities/1499335?utm_content=57341\u0026utm_medium=referral\u0026utm_source=twitter","twitter_msg":"a parcouru 5,5 kilomètre sur Course à pied.","is_new":false,"is_changing_type":false,"suffer_score":null,"calories":1419.4448568000003,"feed_data":{"entries":[]},"workout_type":null,"flagged":false,"hide_power":false,"hide_heartrate":false,"segment_leaderboard_opt_out":false},{"id":1487755,"name":"09/03/2011","type":"Ride","display_type":"Sortie à vélo","activity_type_display_name":"Sortie à vélo","private":false,"bike_id":16588,"athlete_gear_id":null,"start_date":"sam. 3/9/2011","start_date_local_raw":1315066380,"start_time":"2011-09-03T20:13:00+0000","start_day":"Sat","distance":"43,7","distance_raw":43768.4,"long_unit":"kilomètres","short_unit":"km","moving_time":"1:35:11","moving_time_raw":5711,"elapsed_time":"1:44:28","elapsed_time_raw":6268,"trainer":false,"static_map":true,"show_elevation":true,"has_latlng":true,"commute":false,"elevation_gain":"345","elevation_unit":"m","elevation_gain_raw":344.928,"description":"","activity_url":"https://www.strava.com/activities/1487755","activity_url_for_twitter":"https://www.strava.com/activities/1487755?utm_content=57341\u0026utm_medium=referral\u0026utm_source=twitter","twitter_msg":"a parcouru 43,7 kilomètre sur Sortie à vélo.","is_new":false,"is_changing_type":false,"suffer_score":null,"calories":null,"feed_data":{"entries":[]},"workout_type":null,"flagged":false,"hide_power":false,"hide_heartrate":false,"segment_leaderboard_opt_out":false},{"id":34795351,"name":"08/28/2011 Quebec City, QC, Canada","type":"Ride","display_type":"Sortie à vélo","activity_type_display_name":"Sortie à vélo","private":false,"bike_id":null,"athlete_gear_id":null,"start_date":"dim. 28/8/2011","start_date_local_raw":1314498863,"start_time":"2011-08-28T06:34:23+0000","start_day":"Sun","distance":"6,8","distance_raw":6817.17,"long_unit":"kilomètres","short_unit":"km","moving_time":"42:08","moving_time_raw":2528,"elapsed_time":"54:22","elapsed_time_raw":3262,"trainer":false,"static_map":true,"show_elevation":true,"has_latlng":true,"commute":false,"elevation_gain":"155","elevation_unit":"m","elevation_gain_raw":155.092,"description":"","activity_url":"https://www.strava.com/activities/34795351","activity_url_for_twitter":"https://www.strava.com/activities/34795351?utm_content=57341\u0026utm_medium=referral\u0026utm_source=twitter","twitter_msg":"a parcouru 6,8 kilomètre sur Sortie à vélo.","is_new":false,"is_changing_type":false,"suffer_score":null,"calories":413.93748816000004,"feed_data":{"entries":[]},"workout_type":null,"flagged":false,"hide_power":false,"hide_heartrate":false,"segment_leaderboard_opt_out":false},{"id":1308962,"name":"08/20/2011","type":"Run","display_type":"Course","activity_type_display_name":"Course à pied","private":false,"bike_id":null,"athlete_gear_id":null,"start_date":"sam. 20/8/2011","start_date_local_raw":1313850698,"start_time":"2011-08-20T18:31:38+0000","start_day":"Sat","distance":"6,3","distance_raw":6309.23,"long_unit":"kilomètres","short_unit":"km","moving_time":"43:50","moving_time_raw":2630,"elapsed_time":"46:23","elapsed_time_raw":2783,"trainer":false,"static_map":true,"show_elevation":true,"has_latlng":true,"commute":null,"elevation_gain":"203","elevation_unit":"m","elevation_gain_raw":203.28,"description":"Avec poussette.","activity_url":"https://www.strava.com/activities/1308962","activity_url_for_twitter":"https://www.strava.com/activities/1308962?utm_content=57341\u0026utm_medium=referral\u0026utm_source=twitter","twitter_msg":"a parcouru 6,3 kilomètre sur Course à pied.","is_new":false,"is_changing_type":false,"suffer_score":null,"calories":1627.6147030079999,"feed_data":{"entries":[]},"workout_type":null,"flagged":false,"hide_power":false,"hide_heartrate":false,"segment_leaderboard_opt_out":false},{"id":1276636,"name":"08/17/2011","type":"Ride","display_type":"Sortie à vélo","activity_type_display_name":"Sortie à vélo","private":false,"bike_id":16587,"athlete_gear_id":null,"start_date":"mer. 17/8/2011","start_date_local_raw":1313605284,"start_time":"2011-08-17T22:21:24+0000","start_day":"Wed","distance":"6,3","distance_raw":6311.88,"long_unit":"kilomètres","short_unit":"km","moving_time":"52:59","moving_time_raw":3179,"elapsed_time":"1:15:16","elapsed_time_raw":4516,"trainer":false,"static_map":true,"show_elevation":true,"has_latlng":true,"commute":false,"elevation_gain":"165","elevation_unit":"m","elevation_gain_raw":164.747,"description":"","activity_url":"https://www.strava.com/activities/1276636","activity_url_for_twitter":"https://www.strava.com/activities/1276636?utm_content=57341\u0026utm_medium=referral\u0026utm_source=twitter","twitter_msg":"a parcouru 6,3 kilomètre sur Sortie à vélo.","is_new":false,"is_changing_type":false,"suffer_score":null,"calories":null,"feed_data":{"entries":[]},"workout_type":null,"flagged":false,"hide_power":false,"hide_heartrate":false,"segment_leaderboard_opt_out":false},{"id":1277503,"name":"08/16/2011","type":"Ride","display_type":"Sortie à vélo","activity_type_display_name":"Sortie à vélo","private":false,"bike_id":16587,"athlete_gear_id":null,"start_date":"mar. 16/8/2011","start_date_local_raw":1313529620,"start_time":"2011-08-17T01:20:20+0000","start_day":"Tue","distance":"3,6","distance_raw":3644.58,"long_unit":"kilomètres","short_unit":"km","moving_time":"21:40","moving_time_raw":1300,"elapsed_time":"22:01","elapsed_time_raw":1321,"trainer":false,"static_map":true,"show_elevation":true,"has_latlng":true,"commute":false,"elevation_gain":"137","elevation_unit":"m","elevation_gain_raw":136.837,"description":"","activity_url":"https://www.strava.com/activities/1277503","activity_url_for_twitter":"https://www.strava.com/activities/1277503?utm_content=57341\u0026utm_medium=referral\u0026utm_source=twitter","twitter_msg":"a parcouru 3,6 kilomètre sur Sortie à vélo.","is_new":false,"is_changing_type":false,"suffer_score":null,"calories":null,"feed_data":{"entries":[]},"workout_type":null,"flagged":false,"hide_power":false,"hide_heartrate":false,"segment_leaderboard_opt_out":false},{"id":1217814,"name":"08/13/2011","type":"Run","display_type":"Course","activity_type_display_name":"Course à pied","private":false,"bike_id":null,"athlete_gear_id":null,"start_date":"sam. 13/8/2011","start_date_local_raw":1313233680,"start_time":"2011-08-13T15:08:00+0000","start_day":"Sat","distance":"2,0","distance_raw":2086.9,"long_unit":"kilomètres","short_unit":"km","moving_time":"13:21","moving_time_raw":801,"elapsed_time":"13:21","elapsed_time_raw":801,"trainer":false,"static_map":true,"show_elevation":true,"has_latlng":true,"commute":null,"elevation_gain":"33","elevation_unit":"m","elevation_gain_raw":33.3659,"description":"Lamite Strava qui a perdu les 4-5 km courrus avant ce bout là....","activity_url":"https://www.strava.com/activities/1217814","activity_url_for_twitter":"https://www.strava.com/activities/1217814?utm_content=57341\u0026utm_medium=referral\u0026utm_source=twitter","twitter_msg":"a parcouru 2,0 kilomètre sur Course à pied.","is_new":false,"is_changing_type":false,"suffer_score":null,"calories":536.201358192,"feed_data":{"entries":[]},"workout_type":null,"flagged":false,"hide_power":false,"hide_heartrate":false,"segment_leaderboard_opt_out":false},{"id":1147678,"name":"08/07/2011","type":"Run","display_type":"Course","activity_type_display_name":"Course à pied","private":false,"bike_id":null,"athlete_gear_id":null,"start_date":"dim. 7/8/2011","start_date_local_raw":1312732681,"start_time":"2011-08-07T19:58:01+0000","start_day":"Sun","distance":"5,6","distance_raw":5692.86,"long_unit":"kilomètres","short_unit":"km","moving_time":"36:48","moving_time_raw":2208,"elapsed_time":"37:15","elapsed_time_raw":2235,"trainer":false,"static_map":true,"show_elevation":true,"has_latlng":true,"commute":null,"elevation_gain":"166","elevation_unit":"m","elevation_gain_raw":165.935,"description":"Avec la poussette...","activity_url":"https://www.strava.com/activities/1147678","activity_url_for_twitter":"https://www.strava.com/activities/1147678?utm_content=57341\u0026utm_medium=referral\u0026utm_source=twitter","twitter_msg":"a parcouru 5,6 kilomètre sur Course à pied.","is_new":false,"is_changing_type":false,"suffer_score":null,"calories":1353.6121824000002,"feed_data":{"entries":[]},"workout_type":null,"flagged":false,"hide_power":false,"hide_heartrate":false,"segment_leaderboard_opt_out":false},{"id":1112342,"name":"08/05/2011","type":"Ride","display_type":"Sortie à vélo","activity_type_display_name":"Sortie à vélo","private":false,"bike_id":16587,"athlete_gear_id":null,"start_date":"ven. 5/8/2011","start_date_local_raw":1312541273,"start_time":"2011-08-05T14:47:53+0000","start_day":"Fri","distance":"30,1","distance_raw":30145.6,"long_unit":"kilomètres","short_unit":"km","moving_time":"1:36:48","moving_time_raw":5808,"elapsed_time":"1:46:42","elapsed_time_raw":6402,"trainer":false,"static_map":true,"show_elevation":true,"has_latlng":true,"commute":false,"elevation_gain":"400","elevation_unit":"m","elevation_gain_raw":400.255,"description":"","activity_url":"https://www.strava.com/activities/1112342","activity_url_for_twitter":"https://www.strava.com/activities/1112342?utm_content=57341\u0026utm_medium=referral\u0026utm_source=twitter","twitter_msg":"a parcouru 30,1 kilomètre sur Sortie à vélo.","is_new":false,"is_changing_type":false,"suffer_score":null,"calories":null,"feed_data":{"entries":[]},"workout_type":null,"flagged":false,"hide_power":false,"hide_heartrate":false,"segment_leaderboard_opt_out":false},{"id":1096457,"name":"08/04/2011","type":"Run","display_type":"Course","activity_type_display_name":"Course à pied","private":false,"bike_id":null,"athlete_gear_id":null,"start_date":"jeu. 4/8/2011","start_date_local_raw":1312475196,"start_time":"2011-08-04T20:26:36+0000","start_day":"Thu","distance":"2,7","distance_raw":2742.21,"long_unit":"kilomètres","short_unit":"km","moving_time":"24:36","moving_time_raw":1476,"elapsed_time":"43:34","elapsed_time_raw":2614,"trainer":false,"static_map":true,"show_elevation":true,"has_latlng":true,"commute":null,"elevation_gain":"12","elevation_unit":"m","elevation_gain_raw":11.6735,"description":"","activity_url":"https://www.strava.com/activities/1096457","activity_url_for_twitter":"https://www.strava.com/activities/1096457?utm_content=57341\u0026utm_medium=referral\u0026utm_source=twitter","twitter_msg":"a parcouru 2,7 kilomètre sur Course à pied.","is_new":false,"is_changing_type":false,"suffer_score":null,"calories":1273.065327792,"feed_data":{"entries":[]},"workout_type":null,"flagged":false,"hide_power":false,"hide_heartrate":false,"segment_leaderboard_opt_out":false},{"id":1026151,"name":"07/28/2011","type":"Ride","display_type":"Sortie à vélo","activity_type_display_name":"Sortie à vélo","private":false,"bike_id":16587,"athlete_gear_id":null,"start_date":"jeu. 28/7/2011","start_date_local_raw":1311851514,"start_time":"2011-07-28T15:11:54+0000","start_day":"Thu","distance":"9,8","distance_raw":9812.68,"long_unit":"kilomètres","short_unit":"km","moving_time":"1:13:14","moving_time_raw":4394,"elapsed_time":"1:23:45","elapsed_time_raw":5025,"trainer":false,"static_map":true,"show_elevation":true,"has_latlng":true,"commute":false,"elevation_gain":"144","elevation_unit":"m","elevation_gain_raw":144.057,"description":null,"activity_url":"https://www.strava.com/activities/1026151","activity_url_for_twitter":"https://www.strava.com/activities/1026151?utm_content=57341\u0026utm_medium=referral\u0026utm_source=twitter","twitter_msg":"a parcouru 9,8 kilomètre sur Sortie à vélo.","is_new":false,"is_changing_type":false,"suffer_score":null,"calories":null,"feed_data":{"entries":[]},"workout_type":null,"flagged":false,"hide_power":false,"hide_heartrate":false,"segment_leaderboard_opt_out":false},{"id":1020971,"name":"07/27/2011","type":"Ride","display_type":"Sortie à vélo","activity_type_display_name":"Sortie à vélo","private":false,"bike_id":16587,"athlete_gear_id":null,"start_date":"mer. 27/7/2011","start_date_local_raw":1311783283,"start_time":"2011-07-27T20:14:43+0000","start_day":"Wed","distance":"5,9","distance_raw":5969.33,"long_unit":"kilomètres","short_unit":"km","moving_time":"56:05","moving_time_raw":3365,"elapsed_time":"1:00:12","elapsed_time_raw":3612,"trainer":false,"static_map":true,"show_elevation":true,"has_latlng":true,"commute":false,"elevation_gain":"170","elevation_unit":"m","elevation_gain_raw":169.531,"description":null,"activity_url":"https://www.strava.com/activities/1020971","activity_url_for_twitter":"https://www.strava.com/activities/1020971?utm_content=57341\u0026utm_medium=referral\u0026utm_source=twitter","twitter_msg":"a parcouru 5,9 kilomètre sur Sortie à vélo.","is_new":false,"is_changing_type":false,"suffer_score":null,"calories":null,"feed_data":{"entries":[]},"workout_type":null,"flagged":false,"hide_power":false,"hide_heartrate":false,"segment_leaderboard_opt_out":false},{"id":984644,"name":"07/21/2011","type":"Run","display_type":"Course","activity_type_display_name":"Course à pied","private":false,"bike_id":null,"athlete_gear_id":null,"start_date":"jeu. 21/7/2011","start_date_local_raw":1311283291,"start_time":"2011-07-22T01:21:31+0000","start_day":"Thu","distance":"4,6","distance_raw":4642.9,"long_unit":"kilomètres","short_unit":"km","moving_time":"27:12","moving_time_raw":1632,"elapsed_time":"27:12","elapsed_time_raw":1632,"trainer":false,"static_map":true,"show_elevation":true,"has_latlng":true,"commute":null,"elevation_gain":"37","elevation_unit":"m","elevation_gain_raw":37.0672,"description":null,"activity_url":"https://www.strava.com/activities/984644","activity_url_for_twitter":"https://www.strava.com/activities/984644?utm_content=57341\u0026utm_medium=referral\u0026utm_source=twitter","twitter_msg":"a parcouru 4,6 kilomètre sur Course à pied.","is_new":false,"is_changing_type":false,"suffer_score":null,"calories":1105.827235632,"feed_data":{"entries":[]},"workout_type":null,"flagged":false,"hide_power":false,"hide_heartrate":false,"segment_leaderboard_opt_out":false}],"page":32,"perPage":20,"total":719}